sysxinfo/__init__.py
sysxinfo/__main__.py
sysxinfo2-1.0.0.dist-info/LICENSE
sysxinfo2-1.0.0.dist-info/METADATA
sysxinfo2-1.0.0.dist-info/WHEEL
sysxinfo2-1.0.0.dist-info/entry_points.txt
sysxinfo2-1.0.0.dist-info/top_level.txt
sysxinfo2-1.0.0.dist-info/RECORD
