Metadata-Version: 2.1
Name: sysxinfo2
Version: 1.0.0
Summary: Simple CLI tool for watching system Infos
Home-page: https://github.com/srshazin/sysxinfo
Author: Shazin
Author-email: shazin.bd@gmail.com
License: MIT
Platform: UNKNOWN
Classifier: License :: OSI Approved :: MIT License
Classifier: Programming Language :: Python :: 3.6
Classifier: Programming Language :: Python :: 3.7
Classifier: Programming Language :: Python :: 3.8
